{
  "rootId": "root",
  "items": [
    {
      "id": "root",
      "parentId": null,
      "title": "熟練者は丸棒矯正において真直度を安定して規格内に収められるが、新人は再現性が低い",
      "notes": "一次枝は「何がうまくできないか」で切る。二次枝は「そのために何を見たいか、何を決めたいか、何が邪魔をするか」を、そのまま読んで意味が通る言葉にする。"
    },
    {
      "id": "recognition",
      "parentId": "root",
      "title": "曲がりを見つける",
      "notes": "棒がどこでどう曲がっているか、まず目で捉えること。"
    },
    {
      "id": "recognition-target",
      "parentId": "recognition",
      "title": "何を見るか",
      "notes": "どの部位、どの方向、どの大きさの曲がりやまっすぐさを見るのか。"
    },
    {
      "id": "recognition-criteria",
      "parentId": "recognition",
      "title": "どう見えたら曲がりとみなすか",
      "notes": "何をもって「曲がっている」「まっすぐに近い」「まだ直っていない」とみなすのか。"
    },
    {
      "id": "recognition-method",
      "parentId": "recognition",
      "title": "どうやって見るか",
      "notes": "片目、俯瞰、転がし、光の見方、姿勢や持ち方など、どんな見方で曲がりを捉えるのか。"
    },
    {
      "id": "recognition-obstacle",
      "parentId": "recognition",
      "title": "何が見えにくくするか",
      "notes": "遠近感、模様、光、視点の切替など、見え方を崩すもの。"
    },
    {
      "id": "recognition-obstacle-monocular-depth",
      "parentId": "recognition-obstacle",
      "title": "片目だと奥行きがつかみにくい",
      "notes": "片目で見る方法では奥行き感覚を取りにくく、奥側の曲がりを立体的に捉えづらい。"
    },
    {
      "id": "recognition-obstacle-front-dominance",
      "parentId": "recognition-obstacle",
      "title": "手前の曲がりばかり目に入る",
      "notes": "手前側の曲がりが強く見えて、奥側の曲がりを見落としやすい。"
    },
    {
      "id": "localization",
      "parentId": "root",
      "title": "曲がっている場所を決める",
      "notes": "どこが主な曲がりで、どこを直す対象にするかを定めること。"
    },
    {
      "id": "localization-target",
      "parentId": "localization",
      "title": "どの場所を見つけたいか",
      "notes": "主な曲がり位置、押す候補の位置、回転後も追うべき同じ場所。"
    },
    {
      "id": "localization-criteria",
      "parentId": "localization",
      "title": "どこだと判断する決め手は何か",
      "notes": "どこを主な曲がりの場所とみなし、どこを押す候補の場所とみなすのか。"
    },
    {
      "id": "localization-method",
      "parentId": "localization",
      "title": "どうやって場所を追うか",
      "notes": "回転の前後で同じ場所を追う、全体と局所を分けて見る、奥行きを補いながら位置を読むなど、場所を定めるやり方。"
    },
    {
      "id": "localization-obstacle",
      "parentId": "localization",
      "title": "何が場所を見失わせるか",
      "notes": "回転で見失う、手前が強く見える、中央のブレが大きい、歪みが重なるなど、場所決めを崩すもの。"
    },
    {
      "id": "translation",
      "parentId": "root",
      "title": "どこを押すか決める",
      "notes": "見えた曲がりを、押す場所、向き、強さに結びつけること。"
    },
    {
      "id": "translation-target",
      "parentId": "translation",
      "title": "何を押す判断に変えるか",
      "notes": "見えた曲がりを、押す場所、押す向き、押す強さへ変えること。"
    },
    {
      "id": "translation-criteria",
      "parentId": "translation",
      "title": "どこを押せばよいと判断するか",
      "notes": "どこを押せば効くのか、どれくらい押せば足りるのかという決め方。"
    },
    {
      "id": "translation-criteria-press-position",
      "parentId": "translation-criteria",
      "title": "押す場所が合っているか判断しにくい",
      "notes": "プレス時に選んだ場所が本当に正しいとみなせる基準が弱く、押す場所の妥当性を判断しづらい。"
    },
    {
      "id": "translation-criteria-force-hard-material",
      "parentId": "translation-criteria",
      "title": "硬め素材だと押す強さの目安がつかみにくい",
      "notes": "変形した差が見えにくいため、どれくらいのプレス強さが必要かを決めにくい。"
    },
    {
      "id": "translation-method",
      "parentId": "translation",
      "title": "どうやって押し所に落とすか",
      "notes": "一方向ずつ分ける、奥の曲がりを手前の位置感覚に置き換えるなど、見えた形を押し方へ落とすやり方。"
    },
    {
      "id": "translation-obstacle",
      "parentId": "translation",
      "title": "何が押し所を決めにくくするか",
      "notes": "トルネード型、硬い素材、遠近感、視点切替時のぼやけなど、押す場所の判断を崩すもの。"
    },
    {
      "id": "translation-obstacle-tornado-position",
      "parentId": "translation-obstacle",
      "title": "トルネード型だと押す場所に落としにくい",
      "notes": "複数方向の歪みが重なるため、どこを押せば効くかへ結びつけづらい。"
    },
    {
      "id": "evaluation",
      "parentId": "root",
      "title": "押した結果を確かめる",
      "notes": "押したあとに効いたか、足りないか、やりすぎかを確かめること。"
    },
    {
      "id": "evaluation-target",
      "parentId": "evaluation",
      "title": "何を確かめるか",
      "notes": "押したあとに形が変わったか、曲がりが残っているか、規格内に入ったか。"
    },
    {
      "id": "evaluation-criteria",
      "parentId": "evaluation",
      "title": "どこまで変われば足りたとみなすか",
      "notes": "足りた、やりすぎ、十分、まだ足りないをどう見分けるのか。"
    },
    {
      "id": "evaluation-method",
      "parentId": "evaluation",
      "title": "どうやって効きを確かめるか",
      "notes": "プレス前後の差を見る、転がしと目視を照らし合わせる、半分ごとに基準を置くなど、結果の見方。"
    },
    {
      "id": "evaluation-obstacle",
      "parentId": "evaluation",
      "title": "何が効きを見えにくくするか",
      "notes": "硬い素材で差が出にくい、作業者視点ではまっすぐさがつかみにくい、細かい歪みが増えるなど、結果の確認を崩すもの。"
    },
    {
      "id": "evaluation-obstacle-insufficient-press-diff",
      "parentId": "evaluation-obstacle",
      "title": "押し込み不足だと変わったか見えにくい",
      "notes": "押し込み量が足りないと、プレス前後で形が変わったかどうかを確かめにくい。"
    },
    {
      "id": "evaluation-obstacle-hard-material-diff",
      "parentId": "evaluation-obstacle",
      "title": "硬め素材だと変形した差が見えにくい",
      "notes": "割と硬めの素材ではプレス前後の差が出にくく、押した結果を視覚的に判断しにくい。"
    },
    {
      "id": "strategy",
      "parentId": "root",
      "title": "どの順で直すか決める",
      "notes": "曲がりが複数あるときに、どれからどう直すかを決めること。"
    },
    {
      "id": "strategy-target",
      "parentId": "strategy",
      "title": "何を順番づけるか",
      "notes": "弓なり、複数の曲がり、トルネード型の歪みなど、どれを先に扱うかを決める対象。"
    },
    {
      "id": "strategy-criteria",
      "parentId": "strategy",
      "title": "何を先にやるかの決め手は何か",
      "notes": "何を先に取り、どこでやり方を変え、どこで止めるかを決める考え方。"
    },
    {
      "id": "strategy-method",
      "parentId": "strategy",
      "title": "どういう順で直していくか",
      "notes": "一方向ずつ取る、全体から見る、局所から詰める、粗取りから追込へ移るなど、直し方の組み立て。"
    },
    {
      "id": "strategy-obstacle",
      "parentId": "strategy",
      "title": "何が順番を迷わせるか",
      "notes": "曲がりが多い、優先順位が見えない、押しすぎで細かい歪みが増えるなど、直す順番を決めにくくするもの。"
    },
    {
      "id": "maintenance",
      "parentId": "root",
      "title": "同じ精度で作業を続ける",
      "notes": "姿勢、持ち方、視線、集中を保って、見え方や判断の精度を崩さないこと。"
    },
    {
      "id": "maintenance-target",
      "parentId": "maintenance",
      "title": "何を保ち続けるか",
      "notes": "姿勢、持ち方、視線、集中など、作業の精度を保つための土台。"
    },
    {
      "id": "maintenance-criteria",
      "parentId": "maintenance",
      "title": "どんな状態を保てていればよいか",
      "notes": "同じ見え方と同じ判断精度を保てている状態。"
    },
    {
      "id": "maintenance-method",
      "parentId": "maintenance",
      "title": "どうやって崩れを防ぐか",
      "notes": "持ち方、片目と両目の切替、休止、確認のやり方など、再現性を保つ行動。"
    },
    {
      "id": "maintenance-obstacle",
      "parentId": "maintenance",
      "title": "何が精度を崩すか",
      "notes": "長時間作業、疲労、視界のぼやけ、姿勢の崩れなど、精度維持を邪魔するもの。"
    }
  ]
}
